limmat.py
limmat-2019.5.4.320.226294533.dist-info/METADATA
limmat-2019.5.4.320.226294533.dist-info/WHEEL
limmat-2019.5.4.320.226294533.dist-info/top_level.txt
limmat-2019.5.4.320.226294533.dist-info/RECORD
